robino/__init__.py
robino/async_rubino.py
robino/rubino.py
robino/url.py
robino-1.0.3.dist-info/METADATA
robino-1.0.3.dist-info/WHEEL
robino-1.0.3.dist-info/top_level.txt
robino-1.0.3.dist-info/RECORD
