Metadata-Version: 2.1
Name: robino
Version: 1.0.3
Summary: Rubino(Rubika) Library self Bot
Author: Benyamin karimi
Author-email: benkarimi2006@gmail.com
License: MIT
Keywords: rubika,rubino,chat,bot,robot,asyncio,robino
Classifier: Development Status :: 3 - Alpha
Classifier: Intended Audience :: Developers
Classifier: Topic :: Software Development :: Build Tools
Classifier: License :: OSI Approved :: MIT License
Classifier: Programming Language :: Python :: Implementation :: PyPy
Classifier: Programming Language :: Python :: 3
Classifier: Programming Language :: Python :: 3.4
Classifier: Programming Language :: Python :: 3.5
Classifier: Programming Language :: Python :: 3.6
Classifier: Programming Language :: Python :: 3.7
Classifier: Programming Language :: Python :: 3.8
Classifier: Programming Language :: Python :: 3.9
Requires-Dist: requests
Requires-Dist: aiohttp
